redis_yy/__about__.py
redis_yy/__init__.py
redis_yy/redis.py
redis_yy/lib/SERVER_STATUS.py
redis_yy/lib/__init__.py
redis_yy/lib/_compat.py
redis_yy/lib/charset.py
redis_yy/lib/converters.py
redis_yy/lib/settings.py
redis_yy/lib/tool.py
redis_yy/lib/constants/FIELD_TYPE.py
redis_yy/lib/constants/FLAG.py
redis_yy/lib/constants/__init__.py
redis_yy-0.0.8.dist-info/LICENSE
redis_yy-0.0.8.dist-info/METADATA
redis_yy-0.0.8.dist-info/WHEEL
redis_yy-0.0.8.dist-info/top_level.txt
redis_yy-0.0.8.dist-info/RECORD
