Metadata-Version: 2.1
Name: redis-yy
Version: 0.0.8
Summary: A tool which is used to connect redis, designed by yy
Home-page: https://github.com/guaidashu/redis_yy
Author: guaidashu
Author-email: song42960@gmail.com
License: MIT
Platform: UNKNOWN
Classifier: Topic :: Internet :: WWW/HTTP :: Dynamic Content
Classifier: Programming Language :: Python :: 3
Classifier: Programming Language :: Python :: 3.5
Classifier: Programming Language :: Python :: 3.5
Classifier: Programming Language :: Python :: 3.6
Classifier: Programming Language :: Python :: 3.7
Requires-Dist: redis (<=3.3.8)
